YandexWordStatAPI/WordstatAPI.py
YandexWordStatAPI/__init__.py
YandexWordstatAPI-1.1.dist-info/LICENSE
YandexWordstatAPI-1.1.dist-info/METADATA
YandexWordstatAPI-1.1.dist-info/WHEEL
YandexWordstatAPI-1.1.dist-info/top_level.txt
YandexWordstatAPI-1.1.dist-info/RECORD
