Metadata-Version: 2.1
Name: YandexWordstatAPI
Version: 1.1
Summary: Simple class for parsing data from WordStat via yandex direct api
Home-page: https://github.com/Foxdogface/YandexWordstatAPI
Author: Foxdogface and igor-kantor
License: UNKNOWN
Project-URL: Bug Tracker, https://github.com/Foxdogface/YandexWordstatAPI/issues
Platform: UNKNOWN
Classifier: Programming Language :: Python :: 3
Classifier: License :: OSI Approved :: MIT License
Classifier: Operating System :: OS Independent
Requires-Python: >=3.6
License-File: LICENSE
